{
 "based_on": "received_date",
 "chart_name": "Delivered",
 "chart_type": "Count",
 "creation": "2026-02-20 00:00:00.000000",
 "custom_options": "{\"type\": \"bar\", \"height\": 280, \"colors\": [\"#16A34A\"]}",
 "docstatus": 0,
 "doctype": "Dashboard Chart",
 "document_type": "Container",
 "dynamic_filters_json": "[]",
 "filters_json": "[[\"Container\",\"docstatus\",\"!=\",2,false],[\"Container\",\"status\",\"=\",\"Delivered\",false]]",
 "group_by_based_on": "",
 "group_by_type": "Count",
 "idx": 0,
 "is_public": 1,
 "is_standard": 1,
 "modified": "2026-02-20 00:00:00.000000",
 "modified_by": "Administrator",
 "module": "Icd Tz",
 "name": "Delivered",
 "number_of_groups": 0,
 "owner": "Administrator",
 "show_values_over_chart": 0,
 "source": "",
 "time_interval": "Monthly",
 "timeseries": 1,
 "timespan": "Last Year",
 "type": "Bar",
 "use_report_chart": 0,
 "value_based_on": "",
 "roles": [],
 "y_axis": []
}
